evolution/__init__.py
evolution/client.py
evolution/exceptions.py
evolution_client-0.0.1.dist-info/METADATA
evolution_client-0.0.1.dist-info/WHEEL
evolution_client-0.0.1.dist-info/top_level.txt
evolution_client-0.0.1.dist-info/RECORD
