Metadata-Version: 2.1
Name: evolution-client
Version: 0.0.1
Summary: Client Python para a API Evolution
Home-page: UNKNOWN
Author: Davidson Gomes
Author-email: contato@agenciadgcode.com
License: UNKNOWN
Platform: UNKNOWN
Requires-Python: >=3.6
Requires-Dist: requests>=2.25.1
